{
  "name": "leaf",
  "type": "SERVER",
  "language": "JAVA",
  "url": "https://api.leafmc.one/v2/projects/leaf/versions/%version%/builds/%buildId%/downloads/leaf-%version%-%buildId%.jar",
  "arguments": [
    "-nogui"
  ],
  "flags": [],
  "tasks": [
    "EULA_TASK",
    "SPIGOT_SERVER_PROPERTIES",
    "PAPER_PROXY_SUPPORT_TASK"
  ],
  "preTasks": [
    "LOAD_PAPER_DEPENDENCIES_TASK"
  ],
  "versions": [
    {
      "version": "1.21.8",
      "buildId": 143
    },
    {
      "version": "1.21.8",
      "buildId": "139"
    },
    {
      "version": "1.21.8",
      "buildId": 142
    },
    {
      "version": "1.21.7",
      "buildId": 53
    },
    {
      "version": "1.21.6",
      "buildId": 29
    },
    {
      "version": "1.21.5",
      "buildId": 68
    },
    {
      "version": "1.21.4",
      "buildId": 524
    }
  ]
}
